{"version":1,"basis":"entsoe","date":"2026-07-22","generatedAt":"2026-07-24T10:24:39.504Z","perStation":{"way/592157961":{"series":[2867.2,2850.7,2861.2,2875.8,2925.9,2865.4,2379.2,2006.1,1529.8,1228.9,null,null,null,null,null,null,null,null,null,null,null,null,null,null],"periods":10,"avgMW":2439,"peakMW":2925.9,"energyGWh":24.4},"way/35222596":{"series":[0,null,null,null,null,null,null,null,null,null,null,null,null,null,null,null,null,null,null,null,null,null,null,null],"periods":1,"avgMW":0,"peakMW":0,"energyGWh":0},"relation/9399159":{"series":[428.7,471.3,554.9,634.7,635.4,464.2,389.4,463.3,523.8,292.9,null,null,null,null,null,null,null,null,null,null,null,null,null,null],"periods":10,"avgMW":485.8,"peakMW":635.4,"energyGWh":4.9},"way/179252288":{"series":[0,null,null,null,null,null,null,null,null,null,null,null,null,null,null,null,null,null,null,null,null,null,null,null],"periods":1,"avgMW":0,"peakMW":0,"energyGWh":0},"way/386883572":{"series":[1374.8,1381.6,1439.5,1351.6,1455.6,1306.2,1139.2,1034.2,974.6,749,null,null,null,null,null,null,null,null,null,null,null,null,null,null],"periods":10,"avgMW":1220.6,"peakMW":1455.6,"energyGWh":12.2},"way/40049736":{"series":[0,null,null,null,null,null,null,null,null,null,null,null,null,null,null,null,null,null,null,null,null,null,null,null],"periods":1,"avgMW":0,"peakMW":0,"energyGWh":0},"way/40157613":{"series":[350,368.2,364.4,353.8,373.7,366.3,272.8,212.6,188.7,154.4,null,null,null,null,null,null,null,null,null,null,null,null,null,null],"periods":10,"avgMW":300.5,"peakMW":373.7,"energyGWh":3},"way/44961415":{"series":[1733.6,1733.4,1744.4,1752.1,1760.5,1706.5,1260.6,1073.4,1001.8,830.2,null,null,null,null,null,null,null,null,null,null,null,null,null,null],"periods":10,"avgMW":1459.6,"peakMW":1760.5,"energyGWh":14.6},"way/448844031":{"series":[134.1,null,null,44.7,150,213.5,168.9,180.4,175.5,137.1,null,null,null,null,null,null,null,null,null,null,null,null,null,null],"periods":8,"avgMW":150.5,"peakMW":213.5,"energyGWh":1.2},"way/130207099":{"series":[562.1,570.4,580.1,567.3,593.5,526.4,503.6,453.4,416.8,331.4,null,null,null,null,null,null,null,null,null,null,null,null,null,null],"periods":10,"avgMW":510.5,"peakMW":593.5,"energyGWh":5.1},"way/197474976":{"series":[0,null,null,null,null,null,null,null,null,null,null,null,null,null,null,null,null,null,null,null,null,null,null,null],"periods":1,"avgMW":0,"peakMW":0,"energyGWh":0},"way/187420594":{"series":[0,null,null,null,null,null,null,null,null,null,null,null,null,null,null,null,null,null,null,null,null,null,null,null],"periods":1,"avgMW":0,"peakMW":0,"energyGWh":0},"relation/13268627":{"series":[1122.6,929.7,903.7,949,889.7,795.9,659.1,606.2,614.5,322.2,null,null,null,null,null,null,null,null,null,null,null,null,null,null],"periods":10,"avgMW":779.3,"peakMW":1122.6,"energyGWh":7.8},"way/200617506":{"series":[54.6,53.6,40.7,40.4,54.7,54.1,53.3,54.1,54.1,41.1,null,null,null,null,null,null,null,null,null,null,null,null,null,null],"periods":10,"avgMW":50.1,"peakMW":54.7,"energyGWh":0.5},"way/7991621":{"series":[0,null,null,null,null,null,null,null,null,null,null,null,null,null,null,null,null,null,null,null,null,null,null,null],"periods":1,"avgMW":0,"peakMW":0,"energyGWh":0},"way/221120858":{"series":[194.9,195.6,195.4,195.5,195.9,196.9,190.1,137.4,137.2,102.9,null,null,null,null,null,null,null,null,null,null,null,null,null,null],"periods":10,"avgMW":174.2,"peakMW":196.9,"energyGWh":1.7},"way/50778337":{"series":[299,280.1,4.7,null,null,null,null,null,null,null,null,null,null,null,null,null,null,null,null,null,null,null,null,null],"periods":3,"avgMW":194.6,"peakMW":299,"energyGWh":0.6},"way/25898809":{"series":[0,null,null,null,null,null,null,null,null,null,null,null,null,null,null,null,null,null,null,null,null,null,null,null],"periods":1,"avgMW":0,"peakMW":0,"energyGWh":0},"way/1010290944":{"series":[0,null,null,2.7,15.4,25.6,28.2,23.9,47.5,86.3,null,null,null,null,null,null,null,null,null,null,null,null,null,null],"periods":8,"avgMW":28.7,"peakMW":86.3,"energyGWh":0.2},"way/144878941":{"series":[27.9,13.9,14,21,21.9,28.7,16.6,15.3,21,20.8,null,null,null,null,null,null,null,null,null,null,null,null,null,null],"periods":10,"avgMW":20.1,"peakMW":28.7,"energyGWh":0.2}},"mixRows":[{"key":"coal","label":"Coal & lignite","color":"#ad7a45","nowMW":9041,"capMW":0},{"key":"solar","label":"Solar","color":"#c98500","nowMW":5318,"capMW":0},{"key":"wind","label":"Wind","color":"#199e70","nowMW":2477,"capMW":0},{"key":"gas","label":"Gas","color":"#3987e5","nowMW":1664,"capMW":0},{"key":"other","label":"Oil & other","color":"#e66767","nowMW":700,"capMW":0},{"key":"hydro","label":"Hydro & pumped","color":"#1899ac","nowMW":362,"capMW":0},{"key":"biomass","label":"Biomass & waste","color":"#d95926","nowMW":292,"capMW":0},{"key":"imports","label":"Imports (HVDC)","color":"#2dd4bf","nowMW":15,"capMW":0}],"mixSeries":{"biomass":[321,323,319,322,323,319,306,254,229,229,229,225,229,239,257,303,328,327,327,322,324,321,318,317],"coal":[9814,9467,9618,9698,10037,9477,7989,7068,6472,6569,7115,6656,7107,7885,7846,8433,10543,11365,11125,11202,10849,10288,10172,10193],"gas":[2460,2475,2026,1645,2050,2067,1725,1505,1268,1057,1079,1036,1065,1254,1374,1388,1617,1764,2163,2276,2189,1969,1321,1153],"other":[712,715,713,717,734,741,731,703,694,698,696,689,648,653,656,690,693,695,694,696,694,686,722,719],"hydro":[131,131,115,139,168,126,136,129,152,96,126,110,137,126,92,264,661,1323,1366,1289,905,614,194,162],"solar":[0,null,29,600,2342,5330,8415,10078,11137,10832,10248,10144,8734,7149,6642,4874,2904,1290,302,0,null,null,null,null],"wind":[3484,3665,3525,3376,2733,1775,1602,1983,1867,2160,2430,2617,2548,2214,2333,2668,2259,1896,1825,1962,2370,2531,2776,2840]},"flowSeries":{"swepol":[-366,-468,-398,-416,-487,-488,-454,-403,-210,-183,-114,221,130,-205,-307,-381,-373,-487,-366,-487,-488,-366,-488,-366]},"importSeries":[0,0,0,0,0,0,0,0,0,0,0,221,130,0,0,0,0,0,0,0,0,0,0,0],"today":{"date":"2026-07-24","throughHour":10,"mixRows":[{"key":"coal","label":"Coal & lignite","color":"#ad7a45","nowMW":9985,"capMW":0},{"key":"solar","label":"Solar","color":"#c98500","nowMW":4021,"capMW":0},{"key":"wind","label":"Wind","color":"#199e70","nowMW":1729,"capMW":0},{"key":"gas","label":"Gas","color":"#3987e5","nowMW":1621,"capMW":0},{"key":"other","label":"Oil & other","color":"#e66767","nowMW":715,"capMW":0},{"key":"biomass","label":"Biomass & waste","color":"#d95926","nowMW":323,"capMW":0},{"key":"hydro","label":"Hydro & pumped","color":"#1899ac","nowMW":118,"capMW":0},{"key":"imports","label":"Imports (HVDC)","color":"#2dd4bf","nowMW":0,"capMW":0}],"mixSeries":{"biomass":[331,328,333,330,331,329,324,319,309,294,null,null,null,null,null,null,null,null,null,null,null,null,null,null],"coal":[10890,10861,10930,10828,10694,10661,10179,9571,8271,6960,null,null,null,null,null,null,null,null,null,null,null,null,null,null],"gas":[1455,1527,1806,1883,1820,1854,1659,1543,1363,1301,null,null,null,null,null,null,null,null,null,null,null,null,null,null],"other":[723,721,720,726,728,723,718,712,689,686,null,null,null,null,null,null,null,null,null,null,null,null,null,null],"hydro":[123,109,109,108,128,129,126,120,115,114,null,null,null,null,null,null,null,null,null,null,null,null,null,null],"solar":[0,null,24,443,1409,3026,5065,7427,8970,9824,null,null,null,null,null,null,null,null,null,null,null,null,null,null],"wind":[2658,2468,2164,2084,1905,1398,1127,1045,1129,1312,null,null,null,null,null,null,null,null,null,null,null,null,null,null]},"importSeries":[0,0,0,0,0,0,0,0,0,0,null,null,null,null,null,null,null,null,null,null,null,null,null,null],"totalMW":18512,"importMW":0},"mix":{"time":"2026-07-22T12:00:00Z","fuels":[{"key":"coal","label":"Coal & lignite","mw":9041},{"key":"solar","label":"Solar","mw":5318},{"key":"wind","label":"Wind","mw":2477},{"key":"gas","label":"Gas","mw":1664},{"key":"other","label":"Oil & other","mw":700},{"key":"hydro","label":"Hydro & pumped","mw":362},{"key":"biomass","label":"Biomass & waste","mw":292}],"interconnectors":{"swepol":-331},"totalMW":19854,"importMW":15}}