{"byUnit":{"E_ABERDARE":"way/1353839293","E_ABRTW-1":"relation/9599155","T_AFTOW-1":"relation/9298886","E_AIRSW-1":"relation/9346423","T_AKGLW-2":"relation/11561414","T_AKGLW-3":"relation/11561414","T_ANSUW-1":"relation/6949563","E_ARBRB-1":"way/1148898112","T_ARCHW-1":"relation/7872032","E_ASHWW-1":"relation/8835792","E_ASLVW-1":"relation/9418764","E_BABAW-1":"relation/8087058","E_BARNB-1":"way/1149297467","T_BDCHW-1":"relation/9954065","T_BEATO-1":"way/690325130","T_BEATO-2":"way/690325130","T_BEATO-3":"way/690325130","T_BEATO-4":"way/690325130","T_BEINW-1":"relation/9353227","E_BERKB-1":"way/1512575413","E_BERKB-2":"way/1512575413","T_BHLAW-1":"relation/8039767","T_BLKWW-1":"relation/9599113","T_BLLA-2":"relation/2321400","T_BLPFS-1":"relation/19313332","T_BLWNB-1":"way/332532014","E_BNWKW-1":"relation/9584471","T_BOWLW-1":"way/550474153","T_BRBEO-1":"relation/19905799","E_BRDUW-1":"relation/7872124","T_BREDB-1":"way/1476857822","E_BRETB-1":"relation/20254637","E_BRETB-2":"relation/20254637","E_BRGG-1":"way/208495234","E_BRNLW-1":"relation/12863969","E_BROAB-1":"way/1159868562","T_BROCW-1":"relation/19412289","E_BRYBW-1":"relation/8836281","E_BTNHL-1":"way/944261153","E_BTUIW-2":"relation/6949470","E_BTUIW-3":"relation/15016558","E_BURBO":"relation/19905799","E_BURGH-1":"way/843940771","E_BURWB-3":"way/1475040946","T_CARR-1":"way/70311216","T_CARR-2":"way/70311216","T_CDCL-1":"way/402566315","E_CHICK-1":"way/1149497116","E_CHTRY-1":"way/938140160","E_CLAYB-2":"way/1421620456","T_CLDCW-1":"relation/6949277","T_CLDNW-1":"relation/6949277","T_CLDSW-1":"relation/6949277","E_CLFLW-1":"relation/9316516","T_CLVHS-1":"way/810479966","T_CLVHS-2":"way/810479966","E_CMSTW-2":"relation/19465832","E_CNCLW-1":"relation/11522312","T_CNQPS-1":"way/26427510","T_CNQPS-2":"way/26427510","T_CNQPS-3":"way/26427510","T_CNQPS-4":"way/26427510","E_CONTB-1":"way/1148934860","E_CORB-1":"way/97744299","T_COSO-1":"way/913945639","T_COUWW-1":"relation/9319182","T_CREAW-1":"relation/15073556","T_CRGHW-1":"relation/8117328","T_CRMLW-1":"relation/9953388","T_CRUA-1":"way/449382367","T_CRUA-2":"way/449382367","T_CRUA-3":"way/449382367","T_CRUA-4":"way/449382367","T_CRYRW-2":"relation/20113969","T_CRYRW-3":"relation/13616456","T_CRYRW-4":"relation/7872001","T_CUMHW-1":"relation/17296061","T_CUMHW-2":"relation/17296061","E_CWMD-1":"way/230560199","T_DALQW-1":"relation/19405084","E_DALSW-1":"relation/8412487","T_DAMC-1":"way/814351698","T_DBAWO-1":"way/889977926","T_DBAWO-2":"way/889977926","T_DBAWO-3":"way/889977926","T_DBAWO-4":"way/889977926","T_DBAWO-5":"way/889977926","T_DBBWO-1":"way/1157893250","T_DBBWO-2":"way/1157893250","T_DBBWO-3":"way/1157893250","T_DBBWO-4":"way/1157893250","T_DBBWO-5":"way/1157893250","T_DDGNO-1":"way/415308338","T_DDGNO-2":"way/415308338","T_DDGNO-3":"way/415308338","T_DDGNO-4":"way/415308338","E_DIDC1G":"way/945296993","E_DIDC2G":"way/945296993","E_DIDC3G":"way/945296993","E_DIDC4G":"way/945296993","T_DIDCB5":"way/945296994","T_DIDCB6":"way/945296994","T_DINO-1":"relation/6901664","T_DINO-2":"relation/6901664","T_DINO-3":"relation/6901664","T_DINO-4":"relation/6901664","T_DINO-5":"relation/6901664","T_DINO-6":"relation/6901664","E_DOLLB-1":"relation/20679002","T_DOREW-1":"relation/9590825","T_DOREW-2":"relation/9590825","T_DRAXX-1":"way/34383063","T_DRAXX-10G":"way/34383063","T_DRAXX-12G":"way/34383063","T_DRAXX-2":"way/34383063","T_DRAXX-3":"way/34383063","T_DRAXX-4":"way/34383063","T_DRAXX-5":"way/34383063","T_DRAXX-6":"way/34383063","T_DRAXX-9G":"way/34383063","T_DRSLW-1":"relation/12426013","T_DUNGW-1":"relation/9584535","T_DWEXW-1":"relation/19405446","T_EAAO-1":"way/518314314","T_EAAO-2":"way/518314314","T_EDINW-1":"relation/8041182","T_EECL-1":"way/264378992","T_ENHLW-1":"relation/19453343","E_ERSKB-1":"way/1475625561","T_EWHLW-1":"relation/9301579","T_FARR-1":"relation/7872100","T_FARR-2":"relation/7872100","T_FALGW-1":"relation/8185279","E_FAWN-1":"way/1433382874","T_FERRB-1":"way/1476906510","T_FERRB-2":"way/1476906510","T_FFES-1":"way/402796795","T_FFES-2":"way/402796795","T_FFES-3":"way/402796795","T_FFES-4":"way/402796795","T_FINL-1":"way/207523493","T_FOYE-1":"way/449382772","T_FOYE-2":"way/449382772","T_FSDLW-1":"relation/9584763","T_GANW-11":"relation/13386799","T_GANW-22":"relation/13386799","T_GANW-13":"relation/13386799","T_GANW-24":"relation/13386799","E_GFLDW-1":"relation/8394724","E_GLCHW-1":"relation/12862507","T_GLNDO-1":"way/219813087","T_GLNKW-1":"relation/14924868","E_GLOFW-1":"relation/8835818","T_GLWSW-1":"relation/13615670","T_GNAPW-1":"relation/9599112","T_GNFSW-1":"relation/2932605","T_GNFSW-2":"relation/2932605","T_GORDW-2":"relation/13615192","E_GOSHS-1":"way/1153082218","T_GRAI-6":"way/677933700","T_GRAI-7":"way/677933700","T_GRAI-8":"way/677933700","T_GRAI1G":"way/677933700","T_GRAI4G":"way/677933700","E_GRCRB-1":"way/1475218524","T_GRGBW-1":"relation/13386800","T_GRGBW-2":"relation/13386800","T_GRGBW-3":"relation/13386800","E_GRGRW-1":"relation/17984890","T_GRIFW-1":"relation/6949300","T_GRIFW-2":"relation/6949300","E_GYAR-1":"way/201993701","T_GYMR-15":"relation/5474028","T_GYMR-17":"relation/5474028","T_GYMR-26":"relation/5474028","T_GYMR-28":"relation/5474028","T_HADHW-1":"relation/6949332","T_HALSW-1":"relation/12863091","T_HEYM11":"way/310488542","T_HEYM12":"way/310488542","T_HEYM27":"way/310488542","T_HEYM28":"way/310488542","E_HLGLW-1":"relation/9584653","E_HLTWW-1":"relation/8836282","T_HMGTO-1":"way/331863739","T_HMGTO-2":"way/331863739","T_HOWAO-1":"relation/11894296","T_HOWAO-2":"relation/11894296","T_HOWAO-3":"relation/11894296","T_HOWBO-1":"relation/11343101","T_HOWBO-2":"relation/11343101","T_HOWBO-3":"relation/11343101","E_HRHLW-1":"relation/6972691","T_HRSTW-1":"relation/9396198","T_HRTL-1":"way/4800321","T_HRTL-2":"way/4800321","T_HUMR-1":"way/208757000","T_HUMR-2":"way/208757000","T_HUMRD-1":"way/208757000","T_INDQ-1":"way/143791247","T_INDQB-1":"way/143791247","T_IRNAB-1":"way/1512652328","E_JAMBB-2":"way/1421620456","T_KEAD-1":"way/1149621575","T_KEAD-2":"way/1149621575","T_KEADGT-3":"way/1149621575","T_KENNW-1":"relation/15073682","E_KHLLW-1":"relation/17969494","T_KILLPG-1":"way/205132626","T_KILLPG-2":"way/205132626","E_KINCW-1":"way/998559908","T_KLGLW-1":"relation/9396275","T_KLGLW-2":"relation/9396275","E_KLYN-A-1":"way/28390306","T_KPMRW-1":"relation/12863929","T_KYPEW-1":"relation/12863929","T_LAGA-1":"way/178884128","T_LARKB-1":"way/1442566922","T_LARKS-1":"way/1168494496","T_LARYW-1":"way/218433470","T_LARYW-2":"way/218433470","T_LARYW-3":"way/218433470","T_LARYW-4":"way/218433470","T_LBAR-1":"way/38211225","T_LBAR-1G":"way/38211225","T_LCLTW-1":"relation/8085418","T_LIMKW-1":"relation/18617264","E_LITRB-1":"relation/7719816","T_LKSDB-1":"way/1364038290","T_LNCSW-1":"way/550699358","T_LNCSW-2":"way/550699358","E_LYNE1":"way/90009908","E_LYNE2":"way/90009908","E_LYNE3":"way/90009908","E_MARK-1":"way/955984192","E_MDLWH-1":"way/1134093224","T_MEDP-1":"way/150780483","T_MIDMW-1":"relation/12862506","E_MINSW-1":"relation/8836112","T_MKHLW-1":"relation/7998314","E_MORFL-1":"way/1152989938","T_MOWEO-1":"way/895177754","T_MOWEO-2":"way/895177754","T_MOWEO-3":"way/895177754","T_MOWWO-1":"way/1254849361","T_MOWWO-2":"way/1254849361","T_MOWWO-3":"way/1254849361","T_MOWWO-4":"way/1254849361","E_MOYEW-1":"relation/9590773","T_MRWD-1":"way/204595889","T_MYGPW-1":"relation/9343313","T_NANT-1":"way/570076477","E_NEWPB-1":"way/1474381139","E_NEWTB-1":"way/1110596984","T_NNGAO-1":"way/895608597","T_NNGAO-2":"way/895608597","T_NOKYW-1":"relation/19453061","T_NOKYW-2":"relation/19453061","E_NTAWB-1":"way/1512627537","T_NTRVB-1":"way/1419436615","T_NURSB-1":"way/1148939839","T_OMNDW-1":"way/550474159","E_OVRHB-1":"way/1484128931","T_PEHE-1":"way/133329765","T_PEMB-11":"way/16075498","T_PEMB-21":"way/16075498","T_PEMB-31":"way/16075498","T_PEMB-41":"way/16075498","T_PEMB-51":"way/16075498","E_PETEM1":"way/711002156","E_PETEM3":"way/711002156","E_PIBUW-1":"relation/20157713","E_PILLB-1":"way/1116566266","E_PILLB-2":"way/1116566266","T_PNYCB-1":"relation/7906469","T_PNYCW-1":"relation/7906469","E_POTES-1":"way/956010231","E_RAKE-1":"way/1152991020","T_RCBKO-1":"way/565030207","T_RCBKO-2":"way/565030207","E_RDFRB-1":"way/951785974","E_RDFRD-1":"way/951785974","T_RICHB-1":"way/771093003","T_RICHB-2":"way/771093003","T_RMPNO-1":"relation/12617390","T_RMPNO-2":"relation/12617390","T_ROCK-1":"way/29083166","T_RYHPS-1":"way/55955507","T_SAKNW-1":"relation/15520957","T_SCCL-1":"way/312992167","T_SCCL-2":"way/312992167","T_SCCL-3":"way/312992167","T_SEAB-1":"way/4911067","T_SEAB-2":"way/4911067","T_SEEL-1":"way/143902275","T_SGRWO-1":"relation/19268061","T_SGRWO-2":"relation/19268061","T_SGRWO-3":"relation/19268061","T_SGRWO-4":"relation/19268061","T_SGRWO-5":"relation/19268061","T_SGRWO-6":"relation/19268061","T_SHBA-1":"way/204918278","T_SHBA-2":"way/204918278","E_SHOS-1":"way/352871114","T_SHRSW-1":"way/545681226","T_SHRSW-2":"way/545681226","T_SIZB-1":"way/27625744","T_SIZB-2":"way/27625744","E_SKELB-1":"way/1476437942","T_SOFOW-11":"way/1157893252","T_SOFOW-12":"way/1157893252","T_SOFOW-21":"way/1157893252","T_SOFOW-22":"way/1157893252","T_SOKYW-1":"relation/17577116","T_SPLN-1":"way/143902275","T_STAY-1":"way/229449727","T_STAY-2":"way/229449727","T_STAY-3":"way/229449727","T_STAY-4":"way/229449727","T_STLGW-1":"relation/9584598","T_STLGW-2":"relation/9584598","T_STLGW-3":"relation/9584598","E_STRHW-1":"relation/20157404","T_STRNW-1":"relation/8087274","T_SUTB-1":"way/51698894","T_SUTBS-1":"way/51698894","T_SVRP-10":"way/981224694","T_SVRP-20":"way/981224694","T_TDBNW-1":"relation/6949310","E_TDRVE-1":"way/1149233319","T_THNTO-1":"way/113739834","T_THNTO-2":"way/113739834","T_THUPG-1":"relation/19849605","T_THUPG-2":"relation/19849605","T_THURB-1":"way/1122855054","T_THURB-2":"way/1122855054","T_THURB-3":"way/1122855054","E_TGP1":"way/687448641","T_TKNEW-1":"way/790946237","T_TKNWW-1":"way/790946237","E_TLYMW-1":"relation/12815226","T_TORN-1":"way/91104903","T_TORN-2":"way/91104903","T_TSREP-1":"way/100095758","E_TULWW-1":"relation/8849887","T_TYLNS-1":"relation/19293473","E_VKING-2":"relation/15748078","T_VKNGW-1":"relation/15748078","T_VKNGW-2":"relation/15748078","T_VKNGW-3":"relation/15748078","T_VKNGW-4":"relation/15748078","T_WBUGT-1":"way/160279522","T_WBUGT-4":"way/160279522","T_WBURB-1":"way/160279522","T_WBURB-2":"way/160279522","T_WBURB-3":"way/160279522","T_WBURB-41":"way/160279522","T_WBURB-43":"way/160279522","T_WDNSO-1":"way/635728029","T_WDNSO-2":"way/635728029","T_WDRGW-1":"relation/15015645","T_WHIHW-1":"relation/9599092","T_WHILW-1":"relation/2593160","T_WHILW-2":"relation/2593160","E_WHTBB-1":"way/1476530724","T_WILCT-1":"way/77471728","T_WLNYO-2":"relation/8829625","T_WLNYO-3":"relation/8829625","T_WLNYO-4":"relation/8829625","T_WLNYW-1":"relation/8829625","E_WOLVB-1":"way/1512631595","T_WTMSO-1":"way/341804043"},"stations":{"way/1353839293":{"units":[{"b":"E_ABERDARE","name":"Aberdare Power Station","cap":15}]},"relation/9599155":{"units":[{"b":"E_ABRTW-1","name":"Auchrobert Wind Farm","cap":36}]},"relation/9298886":{"units":[{"b":"T_AFTOW-1","name":"Afton Wind Farm","cap":50}]},"relation/9346423":{"units":[{"b":"E_AIRSW-1","name":"Airies","cap":38}]},"relation/11561414":{"units":[{"b":"T_AKGLW-2","name":"AIKENGALL II","cap":64},{"b":"T_AKGLW-3","name":"AIKENGALL2A-W","cap":163}]},"relation/6949563":{"units":[{"b":"T_ANSUW-1","name":"An Suidhe 1","cap":19}]},"way/1148898112":{"units":[{"b":"E_ARBRB-1","name":"Arbroath Battery Storage","cap":35}]},"relation/7872032":{"units":[{"b":"T_ARCHW-1","name":"Arecleoch","cap":114}]},"relation/8835792":{"units":[{"b":"E_ASHWW-1","name":"Andershaw Wind Farm","cap":35}]},"relation/9418764":{"units":[{"b":"E_ASLVW-1","name":"Assel Valley Wind Farm","cap":26}]},"relation/8087058":{"units":[{"b":"E_BABAW-1","name":"Baillie Wind Farm","cap":53}]},"way/1149297467":{"units":[{"b":"E_BARNB-1","name":"Hunningley Stairfoot BESS","cap":44}]},"relation/9954065":{"units":[{"b":"T_BDCHW-1","name":"Bad a Cheo Wind Farm","cap":270}]},"way/690325130":{"units":[{"b":"T_BEATO-1","name":"Beatrice Offshore WF 1","cap":184},{"b":"T_BEATO-2","name":"Beatrice Offshore WF 2","cap":166},{"b":"T_BEATO-3","name":"Beatrice Offshore WF 3","cap":166},{"b":"T_BEATO-4","name":"Beatrice Offshore WF 4","cap":166}]},"relation/9353227":{"units":[{"b":"T_BEINW-1","name":"Beinneun Wind farm","cap":109}]},"way/1512575413":{"units":[{"b":"E_BERKB-1","name":"Berkeley BESS","cap":52},{"b":"E_BERKB-2","name":"Berkeley BESS","cap":52}]},"relation/8039767":{"units":[{"b":"T_BHLAW-1","name":"Bhlaraidh Windfarm 1","cap":108}]},"relation/9599113":{"units":[{"b":"T_BLKWW-1","name":"Blackcraig Windfarm","cap":56}]},"relation/2321400":{"units":[{"b":"T_BLLA-2","name":"Black Law Windfarm Extension","cap":69}]},"relation/19313332":{"units":[{"b":"T_BLPFS-1","name":"Bulphan Fen Warley Green Solar","cap":50}]},"way/332532014":{"units":[{"b":"T_BLWNB-1","name":"Thornton Battery","cap":200}]},"relation/9584471":{"units":[{"b":"E_BNWKW-1","name":"Burn of Whilk Windfarm","cap":23}]},"way/550474153":{"units":[{"b":"T_BOWLW-1","name":"Barrow Offshore Wind","cap":90}]},"relation/19905799":{"units":[{"b":"T_BRBEO-1","name":"BURBO_EXTENSION","cap":258},{"b":"E_BURBO","name":"Burbo Offshore Wind","cap":90}]},"relation/7872124":{"units":[{"b":"E_BRDUW-1","name":"Braes of Doune","cap":74}]},"way/1476857822":{"units":[{"b":"T_BREDB-1","name":"BREDBURY BESS","cap":50}]},"relation/20254637":{"units":[{"b":"E_BRETB-1","name":"Brentwood BESS","cap":52},{"b":"E_BRETB-2","name":"Brentwood BESS","cap":52}]},"way/208495234":{"units":[{"b":"E_BRGG-1","name":"Glanford Brigg","cap":50}]},"relation/12863969":{"units":[{"b":"E_BRNLW-1","name":"Brownieleys","cap":8}]},"way/1159868562":{"units":[{"b":"E_BROAB-1","name":"Broadditch Battery","cap":11}]},"relation/19412289":{"units":[{"b":"T_BROCW-1","name":"Broken Cross WF","cap":48}]},"relation/8836281":{"units":[{"b":"E_BRYBW-1","name":"Berry Burn Wind Farm","cap":63}]},"way/944261153":{"units":[{"b":"E_BTNHL-1","name":"Barton Hill","cap":21}]},"relation/6949470":{"units":[{"b":"E_BTUIW-2","name":"Beinn An Tuirc 2","cap":44}]},"relation/15016558":{"units":[{"b":"E_BTUIW-3","name":"Beinn an Tuirc III Windfarm","cap":52}]},"way/843940771":{"units":[{"b":"E_BURGH-1","name":"Burghfield Power Station","cap":48}]},"way/1475040946":{"units":[{"b":"E_BURWB-3","name":"Burwell 2","cap":30}]},"way/70311216":{"units":[{"b":"T_CARR-1","name":"Carrington Power Ltd - Unit 1","cap":470},{"b":"T_CARR-2","name":"Carrington Power Ltd - Unit 2","cap":470}]},"way/402566315":{"units":[{"b":"T_CDCL-1","name":"T_CDCL-1","cap":445}]},"way/1149497116":{"units":[{"b":"E_CHICK-1","name":"Chickerell Power Station","cap":48}]},"way/938140160":{"units":[{"b":"E_CHTRY-1","name":"Chatterley","cap":20}]},"way/1421620456":{"units":[{"b":"E_CLAYB-2","name":"ClayTye Farm 2 Battery Storage","cap":50},{"b":"E_JAMBB-2","name":"Jamesfield 2 Battery Storage","cap":19}]},"relation/6949277":{"units":[{"b":"T_CLDCW-1","name":"Clyde Central","cap":200},{"b":"T_CLDNW-1","name":"Clyde North","cap":200},{"b":"T_CLDSW-1","name":"Clyde South","cap":150}]},"relation/9316516":{"units":[{"b":"E_CLFLW-1","name":"Clachan Flats","cap":15}]},"way/810479966":{"units":[{"b":"T_CLVHS-1","name":"Cleve Hill Solar 1","cap":112},{"b":"T_CLVHS-2","name":"Cleve Hill Solar 2","cap":205}]},"relation/19465832":{"units":[{"b":"E_CMSTW-2","name":"Camster II","cap":36}]},"relation/11522312":{"units":[{"b":"E_CNCLW-1","name":"Coire Na Cloiche WF","cap":31}]},"way/26427510":{"units":[{"b":"T_CNQPS-1","name":"T_CNQPS-1","cap":351},{"b":"T_CNQPS-2","name":"T_CNQPS-2","cap":352},{"b":"T_CNQPS-3","name":"T_CNQPS-3","cap":352},{"b":"T_CNQPS-4","name":"T_CNQPS-4","cap":352}]},"way/1148934860":{"units":[{"b":"E_CONTB-1","name":"Contego Battery","cap":36}]},"way/97744299":{"units":[{"b":"E_CORB-1","name":"CORBY POWER LIMITED","cap":240}]},"way/913945639":{"units":[{"b":"T_COSO-1","name":"Coryton Power Station","cap":856}]},"relation/9319182":{"units":[{"b":"T_COUWW-1","name":"Cour Wind Farm","cap":21}]},"relation/15073556":{"units":[{"b":"T_CREAW-1","name":"Creag Riabhach Wind Farm","cap":93}]},"relation/8117328":{"units":[{"b":"T_CRGHW-1","name":"Carraig Gheal Wind Farm","cap":46}]},"relation/9953388":{"units":[{"b":"T_CRMLW-1","name":"Corriemoillie","cap":48}]},"way/449382367":{"units":[{"b":"T_CRUA-1","name":"T_CRUA-1","cap":123},{"b":"T_CRUA-2","name":"T_CRUA-2","cap":125},{"b":"T_CRUA-3","name":"T_CRUA-3","cap":101},{"b":"T_CRUA-4","name":"T_CRUA-4","cap":104}]},"relation/20113969":{"units":[{"b":"T_CRYRW-2","name":"Crystal Rig II Windfarm","cap":151}]},"relation/13616456":{"units":[{"b":"T_CRYRW-3","name":"Crystal Rig III","cap":14}]},"relation/7872001":{"units":[{"b":"T_CRYRW-4","name":"Crystal Rig IV Wind Farm","cap":48}]},"relation/17296061":{"units":[{"b":"T_CUMHW-1","name":"Cumberhead wind energy limited","cap":52},{"b":"T_CUMHW-2","name":"T_CUMHW-2","cap":126}]},"way/230560199":{"units":[{"b":"E_CWMD-1","name":"Cwm Dyli","cap":10}]},"relation/19405084":{"units":[{"b":"T_DALQW-1","name":"Dalquhandy  Wind Farm","cap":43}]},"relation/8412487":{"units":[{"b":"E_DALSW-1","name":"Dalswinton Windfarm","cap":30}]},"way/814351698":{"units":[{"b":"T_DAMC-1","name":"Damhead Creek Ltd.","cap":820}]},"way/889977926":{"units":[{"b":"T_DBAWO-1","name":"Dogger Bank A Offshore WF 1","cap":302},{"b":"T_DBAWO-2","name":"Dogger Bank A Offshore WF 2","cap":304},{"b":"T_DBAWO-3","name":"Dogger Bank A Offshore WF 3","cap":303},{"b":"T_DBAWO-4","name":"Dogger Bank A Offshore WF 4","cap":153},{"b":"T_DBAWO-5","name":"Dogger Bank A Offshore WF 5","cap":138}]},"way/1157893250":{"units":[{"b":"T_DBBWO-1","name":"Dogger Bank B Offshore WF 1","cap":302},{"b":"T_DBBWO-2","name":"Dogger Bank B Offshore WF 2","cap":304},{"b":"T_DBBWO-3","name":"Dogger Bank B Offshore WF 3","cap":302},{"b":"T_DBBWO-4","name":"Dogger Bank B Offshore WF 4","cap":152},{"b":"T_DBBWO-5","name":"Dogger Bank B Offshore WF 5","cap":139}]},"way/415308338":{"units":[{"b":"T_DDGNO-1","name":"Dudgeon Generator BMU 1","cap":108},{"b":"T_DDGNO-2","name":"Dudgeon Generator BMU 2","cap":90},{"b":"T_DDGNO-3","name":"Dudgeon Generator BMU 3","cap":102},{"b":"T_DDGNO-4","name":"Dudgeon Generator BMU 4","cap":102}]},"way/945296993":{"units":[{"b":"E_DIDC1G","name":"Didcot OCGT Unit 1","cap":25},{"b":"E_DIDC2G","name":"Didcot OCGT Unit 2","cap":25},{"b":"E_DIDC3G","name":"Didcot OCGT Unit 3","cap":25},{"b":"E_DIDC4G","name":"Didcot OCGT Unit 4","cap":25}]},"way/945296994":{"units":[{"b":"T_DIDCB5","name":"Didcot B main unit 5","cap":770},{"b":"T_DIDCB6","name":"Didcot B main unit 6","cap":720}]},"relation/6901664":{"units":[{"b":"T_DINO-1","name":"Dinorwig 1","cap":320},{"b":"T_DINO-2","name":"Dinorwig 2","cap":320},{"b":"T_DINO-3","name":"Dinorwig 3","cap":320},{"b":"T_DINO-4","name":"Dinorwig 4","cap":320},{"b":"T_DINO-5","name":"Dinorwig 5","cap":320},{"b":"T_DINO-6","name":"Dinorwig 6","cap":320}]},"relation/20679002":{"units":[{"b":"E_DOLLB-1","name":"Dollymans Storage","cap":102}]},"relation/9590825":{"units":[{"b":"T_DOREW-1","name":"Dorenell Wind Farm One","cap":157},{"b":"T_DOREW-2","name":"Dorenell Wind Farm Two","cap":157}]},"way/34383063":{"units":[{"b":"T_DRAXX-1","name":"T_DRAXX-1","cap":665},{"b":"T_DRAXX-10G","name":"T_DRAXX-10G","cap":33},{"b":"T_DRAXX-12G","name":"T_DRAXX-12G","cap":32},{"b":"T_DRAXX-2","name":"T_DRAXX-2","cap":669},{"b":"T_DRAXX-3","name":"T_DRAXX-3","cap":661},{"b":"T_DRAXX-4","name":"T_DRAXX-4","cap":645},{"b":"T_DRAXX-5","name":"T_DRAXX-5","cap":645},{"b":"T_DRAXX-6","name":"T_DRAXX-6","cap":645},{"b":"T_DRAXX-9G","name":"T_DRAXX-9G","cap":32}]},"relation/12426013":{"units":[{"b":"T_DRSLW-1","name":"Dersalloch Windfarm","cap":71}]},"relation/9584535":{"units":[{"b":"T_DUNGW-1","name":"Dunmglass Windfarm 1","cap":100}]},"relation/19405446":{"units":[{"b":"T_DWEXW-1","name":"Douglas West Extension","cap":66}]},"way/518314314":{"units":[{"b":"T_EAAO-1","name":"East Anglia One Offshore 1","cap":358},{"b":"T_EAAO-2","name":"East Anglia One Offshore 2","cap":367}]},"relation/8041182":{"units":[{"b":"T_EDINW-1","name":"Edinbane Windfarm","cap":41}]},"way/264378992":{"units":[{"b":"T_EECL-1","name":"Enfield Energy Centre Ltd BMU1","cap":444}]},"relation/19453343":{"units":[{"b":"T_ENHLW-1","name":"Enoch Hill Wind Farm","cap":70}]},"way/1475625561":{"units":[{"b":"E_ERSKB-1","name":"Erskine BESS","cap":30}]},"relation/9301579":{"units":[{"b":"T_EWHLW-1","name":"Ewe Hill II Windfarm","cap":38}]},"relation/7872100":{"units":[{"b":"T_FARR-1","name":"Farr Unit 1","cap":92},{"b":"T_FARR-2","name":"Farr Unit 2","cap":92}]},"relation/8185279":{"units":[{"b":"T_FALGW-1","name":"Fallago Rig Wind Farm","cap":144}]},"way/1433382874":{"units":[{"b":"E_FAWN-1","name":"Fawley Cogen","cap":155}]},"way/1476906510":{"units":[{"b":"T_FERRB-1","name":"Ferrybridge BESS BMU-1","cap":76},{"b":"T_FERRB-2","name":"Ferrybridge BESS BMU-2","cap":76}]},"way/402796795":{"units":[{"b":"T_FFES-1","name":"Ffestioniog 1","cap":91},{"b":"T_FFES-2","name":"Ffestioniog 2","cap":92},{"b":"T_FFES-3","name":"Ffestioniog 3","cap":91},{"b":"T_FFES-4","name":"Ffestioniog 4","cap":91}]},"way/207523493":{"units":[{"b":"T_FINL-1","name":"Finlarig","cap":86}]},"way/449382772":{"units":[{"b":"T_FOYE-1","name":"Foyers G1","cap":160},{"b":"T_FOYE-2","name":"Foyers G2","cap":160}]},"relation/9584763":{"units":[{"b":"T_FSDLW-1","name":"Freasdail Wind Farm","cap":22}]},"relation/13386799":{"units":[{"b":"T_GANW-11","name":"Galloper OSP 11","cap":88},{"b":"T_GANW-22","name":"Galloper OSP 22","cap":386},{"b":"T_GANW-13","name":"Galloper OSP 13","cap":88},{"b":"T_GANW-24","name":"Galloper OSP 24","cap":88}]},"relation/8394724":{"units":[{"b":"E_GFLDW-1","name":"Goole Fields Wind Farm","cap":33}]},"relation/12862507":{"units":[{"b":"E_GLCHW-1","name":"Glenchamber","cap":27}]},"way/219813087":{"units":[{"b":"T_GLNDO-1","name":"Glendoe Generator 1","cap":100}]},"relation/14924868":{"units":[{"b":"T_GLNKW-1","name":"GLEN KYLLACHY WINDFARM","cap":52}]},"relation/8835818":{"units":[{"b":"E_GLOFW-1","name":"Glens of Foudland","cap":27}]},"relation/13615670":{"units":[{"b":"T_GLWSW-1","name":"Galawhistle Wind Farm","cap":55}]},"relation/9599112":{"units":[{"b":"T_GNAPW-1","name":"Glen App Windfarm","cap":22}]},"relation/2932605":{"units":[{"b":"T_GNFSW-1","name":"Gunfleet Sands 1","cap":108},{"b":"T_GNFSW-2","name":"Gunfleet Sands 2","cap":64}]},"relation/13615192":{"units":[{"b":"T_GORDW-2","name":"Gordonbush WF Extension","cap":59}]},"way/1153082218":{"units":[{"b":"E_GOSHS-1","name":"Goose House Lane","cap":20}]},"way/677933700":{"units":[{"b":"T_GRAI-6","name":"T_GRAI-6","cap":468},{"b":"T_GRAI-7","name":"T_GRAI-7","cap":468},{"b":"T_GRAI-8","name":"T_GRAI-8","cap":468},{"b":"T_GRAI1G","name":"T_GRAI1G","cap":30},{"b":"T_GRAI4G","name":"T_GRAI4G","cap":29}]},"way/1475218524":{"units":[{"b":"E_GRCRB-1","name":"Gerrards Cross BESS","cap":20}]},"relation/13386800":{"units":[{"b":"T_GRGBW-1","name":"Greater Gabbard Module 1","cap":240},{"b":"T_GRGBW-2","name":"Greater Gabbard Module 2","cap":240},{"b":"T_GRGBW-3","name":"Greater Gabbard Module 3","cap":240}]},"relation/17984890":{"units":[{"b":"E_GRGRW-1","name":"Greengairs East WF-1","cap":38}]},"relation/6949300":{"units":[{"b":"T_GRIFW-1","name":"Griffin Wind Farm 1","cap":102},{"b":"T_GRIFW-2","name":"Griffin Wind Farm 2","cap":104}]},"way/201993701":{"units":[{"b":"E_GYAR-1","name":"Great Yarmouth Power Limited","cap":402}]},"relation/5474028":{"units":[{"b":"T_GYMR-15","name":"GyM OSPE 15","cap":148},{"b":"T_GYMR-17","name":"GyM OSPE 17","cap":148},{"b":"T_GYMR-26","name":"GyM OSPW 26","cap":148},{"b":"T_GYMR-28","name":"GyM OSPW 28","cap":148}]},"relation/6949332":{"units":[{"b":"T_HADHW-1","name":"Hadyard Hill Wind Farm","cap":130}]},"relation/12863091":{"units":[{"b":"T_HALSW-1","name":"Halsary Windfarm","cap":30}]},"way/310488542":{"units":[{"b":"T_HEYM11","name":"Heysham 1 Generator 1","cap":610},{"b":"T_HEYM12","name":"Heysham 1 Generator 2","cap":585},{"b":"T_HEYM27","name":"Heysham 2 Generator 7","cap":660},{"b":"T_HEYM28","name":"Heysham 2 Generator 8","cap":676}]},"relation/9584653":{"units":[{"b":"E_HLGLW-1","name":"Hill of Glaschyle","cap":28}]},"relation/8836282":{"units":[{"b":"E_HLTWW-1","name":"Hill of Towie","cap":48}]},"way/331863739":{"units":[{"b":"T_HMGTO-1","name":"Humber Offshore Wind Farm BMU1","cap":108},{"b":"T_HMGTO-2","name":"Humber Offshore Wind Farm BMU2","cap":111}]},"relation/11894296":{"units":[{"b":"T_HOWAO-1","name":"HORNSEA_1A","cap":400},{"b":"T_HOWAO-2","name":"HORNSEA_1B","cap":400},{"b":"T_HOWAO-3","name":"HORNSEA_1C","cap":400}]},"relation/11343101":{"units":[{"b":"T_HOWBO-1","name":"HORNSEA_WF_2A","cap":440},{"b":"T_HOWBO-2","name":"HORNSEA_WF_2B","cap":440},{"b":"T_HOWBO-3","name":"HORNSEA_WF_2C","cap":440}]},"relation/6972691":{"units":[{"b":"E_HRHLW-1","name":"Hare Hill Extension Windfarm","cap":30}]},"relation/9396198":{"units":[{"b":"T_HRSTW-1","name":"Harestanes","cap":142}]},"way/4800321":{"units":[{"b":"T_HRTL-1","name":"Hartlepool Generator 1","cap":620},{"b":"T_HRTL-2","name":"Hartlepool Generator 2","cap":620}]},"way/208757000":{"units":[{"b":"T_HUMR-1","name":"HUMR-1","cap":1283},{"b":"T_HUMR-2","name":"HUMR-2","cap":50},{"b":"T_HUMRD-1","name":"HUMRD-1","cap":20}]},"way/143791247":{"units":[{"b":"T_INDQ-1","name":"Gas Turbine","cap":140},{"b":"T_INDQB-1","name":"INDIAN QUEENS BESS","cap":48}]},"way/1512652328":{"units":[{"b":"T_IRNAB-1","name":"Iron Acton","cap":121}]},"way/1149621575":{"units":[{"b":"T_KEAD-1","name":"KGL CCGT 1","cap":764},{"b":"T_KEAD-2","name":"Keadby-2 Main","cap":890},{"b":"T_KEADGT-3","name":"KGL GT 3","cap":30}]},"relation/15073682":{"units":[{"b":"T_KENNW-1","name":"Kennoxhead Wind Farm","cap":60}]},"relation/17969494":{"units":[{"b":"E_KHLLW-1","name":"Kirk Hill WF","cap":19}]},"way/205132626":{"units":[{"b":"T_KILLPG-1","name":"T_KILLPG-1","cap":311},{"b":"T_KILLPG-2","name":"T_KILLPG-2","cap":316}]},"way/998559908":{"units":[{"b":"E_KINCW-1","name":"Kincardine Offshore Windfarm","cap":50}]},"relation/9396275":{"units":[{"b":"T_KLGLW-1","name":"Kilgallioch Windfarm","cap":253},{"b":"T_KLGLW-2","name":"T_KLGLW-2","cap":225}]},"way/28390306":{"units":[{"b":"E_KLYN-A-1","name":"Kings Lynn A","cap":392}]},"relation/12863929":{"units":[{"b":"T_KPMRW-1","name":"KYPE MUIR WIND FARM","cap":89},{"b":"T_KYPEW-1","name":"KYPE MUIR EXT WIND FARM","cap":67}]},"way/178884128":{"units":[{"b":"T_LAGA-1","name":"Langage Power Station","cap":905}]},"way/1442566922":{"units":[{"b":"T_LARKB-1","name":"Larks Green Battery Storage","cap":52}]},"way/1168494496":{"units":[{"b":"T_LARKS-1","name":"Larks Green Solar","cap":50}]},"way/218433470":{"units":[{"b":"T_LARYW-1","name":"London Array BMU1","cap":171},{"b":"T_LARYW-2","name":"London Array BMU2","cap":171},{"b":"T_LARYW-3","name":"London Array BMU3","cap":171},{"b":"T_LARYW-4","name":"London Array BMU4","cap":191}]},"way/38211225":{"units":[{"b":"T_LBAR-1","name":"Little Barford main unit 1","cap":750},{"b":"T_LBAR-1G","name":"Little Barford OCGT","cap":25}]},"relation/8085418":{"units":[{"b":"T_LCLTW-1","name":"Lochluichart Windfarm","cap":69}]},"relation/18617264":{"units":[{"b":"T_LIMKW-1","name":"Limekiln Wind Farm","cap":106}]},"relation/7719816":{"units":[{"b":"E_LITRB-1","name":"Little Raith BESS","cap":50}]},"way/1364038290":{"units":[{"b":"T_LKSDB-1","name":"Lakeside  BESS","cap":105}]},"way/550699358":{"units":[{"b":"T_LNCSW-1","name":"Lincs wind farm offshore BMU1","cap":150},{"b":"T_LNCSW-2","name":"Lincs wind farm offshore BMU2","cap":150}]},"way/90009908":{"units":[{"b":"E_LYNE1","name":"LYNEMOUTH GENERATOR 1","cap":140},{"b":"E_LYNE2","name":"LYNEMOUTH GENERATOR 2","cap":140},{"b":"E_LYNE3","name":"LYNEMOUTH GENERATOR 3","cap":140}]},"way/955984192":{"units":[{"b":"E_MARK-1","name":"Rothes Bio-Plant CHP1","cap":86}]},"way/1134093224":{"units":[{"b":"E_MDLWH-1","name":"Middlewich","cap":20}]},"way/150780483":{"units":[{"b":"T_MEDP-1","name":"Medway Power","cap":750}]},"relation/12862506":{"units":[{"b":"T_MIDMW-1","name":"MIDDLE MUIR WIND FARM","cap":51}]},"relation/8836112":{"units":[{"b":"E_MINSW-1","name":"Minsca Wind Farm","cap":38}]},"relation/7998314":{"units":[{"b":"T_MKHLW-1","name":"Mark Hill","cap":54}]},"way/1152989938":{"units":[{"b":"E_MORFL-1","name":"Moorfield Drive","cap":20}]},"way/895177754":{"units":[{"b":"T_MOWEO-1","name":"Moray East OWF1","cap":300},{"b":"T_MOWEO-2","name":"Moray East OWF2","cap":300},{"b":"T_MOWEO-3","name":"Moray East OWF3","cap":300}]},"way/1254849361":{"units":[{"b":"T_MOWWO-1","name":"Moray West OWF1","cap":215},{"b":"T_MOWWO-2","name":"Moray West OWF2","cap":215},{"b":"T_MOWWO-3","name":"Moray West OWF3","cap":143},{"b":"T_MOWWO-4","name":"Moray West OWF4","cap":287}]},"relation/9590773":{"units":[{"b":"E_MOYEW-1","name":"Moy Windfarm","cap":60}]},"way/204595889":{"units":[{"b":"T_MRWD-1","name":"Marchwood Power Ltd","cap":920}]},"relation/9343313":{"units":[{"b":"T_MYGPW-1","name":"Minnygap Wind Farm","cap":25}]},"way/570076477":{"units":[{"b":"T_NANT-1","name":"Nant","cap":20}]},"way/1474381139":{"units":[{"b":"E_NEWPB-1","name":"Newport BESS","cap":21}]},"way/1110596984":{"units":[{"b":"E_NEWTB-1","name":"Newton wood BESS","cap":52}]},"way/895608597":{"units":[{"b":"T_NNGAO-1","name":"Neart Na Gaiothe WF 1","cap":224},{"b":"T_NNGAO-2","name":"Neart Na Gaiothe WF 2","cap":224}]},"relation/19453061":{"units":[{"b":"T_NOKYW-1","name":"North Kyle Wind Farm-1","cap":106},{"b":"T_NOKYW-2","name":"North Kyle Wind Farm-2","cap":106}]},"way/1512627537":{"units":[{"b":"E_NTAWB-1","name":"North Tawton BESS","cap":32}]},"way/1419436615":{"units":[{"b":"T_NTRVB-1","name":"Native River","cap":57}]},"way/1148939839":{"units":[{"b":"T_NURSB-1","name":"Nursling Battery Storage","cap":48}]},"way/550474159":{"units":[{"b":"T_OMNDW-1","name":"Ormonde Energy Limited 1","cap":151}]},"way/1484128931":{"units":[{"b":"E_OVRHB-1","name":"Overhill BESS","cap":49}]},"way/133329765":{"units":[{"b":"T_PEHE-1","name":"Peterhead Block 1","cap":1200}]},"way/16075498":{"units":[{"b":"T_PEMB-11","name":"Pembroke Unit 11","cap":475},{"b":"T_PEMB-21","name":"Pembroke Unit 21","cap":475},{"b":"T_PEMB-31","name":"Pembroke Unit 31","cap":475},{"b":"T_PEMB-41","name":"Pembroke Unit 41","cap":475},{"b":"T_PEMB-51","name":"Pembroke Unit 51","cap":475}]},"way/711002156":{"units":[{"b":"E_PETEM1","name":"Peterborough","cap":245},{"b":"E_PETEM3","name":"Peterborough Power 3","cap":49}]},"relation/20157713":{"units":[{"b":"E_PIBUW-1","name":"Pines Burn Wind Farm","cap":36}]},"way/1116566266":{"units":[{"b":"E_PILLB-1","name":"Pillswood 1 Battery Storage","cap":50},{"b":"E_PILLB-2","name":"Pillswood 2 Battery Storage","cap":50}]},"relation/7906469":{"units":[{"b":"T_PNYCB-1","name":"Pen y Cymoedd Battery","cap":22},{"b":"T_PNYCW-1","name":"PNYCW-1 Export","cap":228}]},"way/956010231":{"units":[{"b":"E_POTES-1","name":"Port of Tyne Energy Storage","cap":35}]},"way/1152991020":{"units":[{"b":"E_RAKE-1","name":"Rake Lane","cap":20}]},"way/565030207":{"units":[{"b":"T_RCBKO-1","name":"RACE_BANK_Z01","cap":284},{"b":"T_RCBKO-2","name":"RACE_BANK_Z02","cap":290}]},"way/951785974":{"units":[{"b":"E_RDFRB-1","name":"Redfield Road B","cap":20},{"b":"E_RDFRD-1","name":"Redfield Road","cap":21}]},"way/771093003":{"units":[{"b":"T_RICHB-1","name":"Richborough Energy Park 1","cap":50},{"b":"T_RICHB-2","name":"Richborough Energy Park 2","cap":50}]},"relation/12617390":{"units":[{"b":"T_RMPNO-1","name":"Rampion Offshore Wind BMU 1","cap":200},{"b":"T_RMPNO-2","name":"Rampion Offshore Wind BMU 2","cap":200}]},"way/29083166":{"units":[{"b":"T_ROCK-1","name":"Rocksavage Power Station","cap":810}]},"way/55955507":{"units":[{"b":"T_RYHPS-1","name":"T_RYHPS-1","cap":721}]},"relation/15520957":{"units":[{"b":"T_SAKNW-1","name":"Sandy Knowe Wind Farm","cap":87}]},"way/312992167":{"units":[{"b":"T_SCCL-1","name":"Unit 1","cap":408},{"b":"T_SCCL-2","name":"Unit 2","cap":409},{"b":"T_SCCL-3","name":"Unit 3","cap":409}]},"way/4911067":{"units":[{"b":"T_SEAB-1","name":"Seabank Power Module","cap":830},{"b":"T_SEAB-2","name":"Seabank Power Module 2","cap":406}]},"way/143902275":{"units":[{"b":"T_SEEL-1","name":"Spalding Energy Expansion Ltd","cap":300},{"b":"T_SPLN-1","name":"Spalding Power Station","cap":950}]},"relation/19268061":{"units":[{"b":"T_SGRWO-1","name":"Seagreen1 Offshore WF 1","cap":431},{"b":"T_SGRWO-2","name":"Seagreen1 Offshore WF 2","cap":220},{"b":"T_SGRWO-3","name":"Seagreen1 Offshore WF 3","cap":375},{"b":"T_SGRWO-4","name":"Seagreen1 Offshore WF 4","cap":140},{"b":"T_SGRWO-5","name":"Seagreen1 Offshore WF 5","cap":300},{"b":"T_SGRWO-6","name":"Seagreen1 Offshore WF 6","cap":525}]},"way/204918278":{"units":[{"b":"T_SHBA-1","name":"SOUTH HUMBER BANK P/S PHASE 1","cap":821},{"b":"T_SHBA-2","name":"SOUTH HUMBER BANK P/S PHASE 2","cap":580}]},"way/352871114":{"units":[{"b":"E_SHOS-1","name":"Shoreham Power Station","cap":460}]},"way/545681226":{"units":[{"b":"T_SHRSW-1","name":"Sheringham Shoal Unit 1","cap":158},{"b":"T_SHRSW-2","name":"Sheringham Shoal Unit 2","cap":158}]},"way/27625744":{"units":[{"b":"T_SIZB-1","name":"Sizewell B Genrator 1","cap":657},{"b":"T_SIZB-2","name":"Sizewell B Genrator 2","cap":630}]},"way/1476437942":{"units":[{"b":"E_SKELB-1","name":"Skelmersdale Battery","cap":50}]},"way/1157893252":{"units":[{"b":"T_SOFOW-11","name":"Sofia Offshore Wind BMU 1","cap":457},{"b":"T_SOFOW-12","name":"Sofia Offshore Wind BMU 2","cap":457},{"b":"T_SOFOW-21","name":"Sofia Offshore Wind BMU 3","cap":457},{"b":"T_SOFOW-22","name":"Sofia Offshore Wind BMU 4","cap":457}]},"relation/17577116":{"units":[{"b":"T_SOKYW-1","name":"South Kyle Wind Farm","cap":427}]},"way/229449727":{"units":[{"b":"T_STAY-1","name":"Staythorpe Unit 1","cap":464},{"b":"T_STAY-2","name":"Staythorpe Unit 2","cap":464},{"b":"T_STAY-3","name":"Staythorpe Unit 3","cap":464},{"b":"T_STAY-4","name":"Staythorpe Unit 4","cap":464}]},"relation/9584598":{"units":[{"b":"T_STLGW-1","name":"Stronelairg Windfarm 1","cap":108},{"b":"T_STLGW-2","name":"Stronelairg Windfarm 2","cap":108},{"b":"T_STLGW-3","name":"Stronelairg Windfarm 3","cap":108}]},"relation/20157404":{"units":[{"b":"E_STRHW-1","name":"Strathrory Wind Farm","cap":36}]},"relation/8087274":{"units":[{"b":"T_STRNW-1","name":"Strathy North Wind Farm 1","cap":70}]},"way/51698894":{"units":[{"b":"T_SUTB-1","name":"BMUid for Sutton Bridge Power","cap":850},{"b":"T_SUTBS-1","name":"Sutton Bridge Solar Farm","cap":49}]},"way/981224694":{"units":[{"b":"T_SVRP-10","name":"Dong Energy Severn Power Ut 10","cap":425},{"b":"T_SVRP-20","name":"Dong Energy Severn Power Ut 20","cap":425}]},"relation/6949310":{"units":[{"b":"T_TDBNW-1","name":"Toddleburn","cap":32}]},"way/1149233319":{"units":[{"b":"E_TDRVE-1","name":"The Drove","cap":6}]},"way/113739834":{"units":[{"b":"T_THNTO-1","name":"Thanet Offshore Wind Limited 1","cap":288},{"b":"T_THNTO-2","name":"Thanet Offshore Wind Limited 2","cap":230}]},"relation/19849605":{"units":[{"b":"T_THUPG-1","name":"T_THUPG-1","cap":180},{"b":"T_THUPG-2","name":"T_THUPG-2","cap":170}]},"way/1122855054":{"units":[{"b":"T_THURB-1","name":"T_THURB-1","cap":100},{"b":"T_THURB-2","name":"T_THURB-2","cap":100},{"b":"T_THURB-3","name":"T_THURB-3","cap":100}]},"way/687448641":{"units":[{"b":"E_TGP1","name":"Tilbury Green Power One","cap":43}]},"way/790946237":{"units":[{"b":"T_TKNEW-1","name":"Triton Knoll OSP East 1","cap":412},{"b":"T_TKNWW-1","name":"Triton Knoll OSP west 1","cap":412}]},"relation/12815226":{"units":[{"b":"E_TLYMW-1","name":"Tullymurdoch Wind Farm","cap":14}]},"way/91104903":{"units":[{"b":"T_TORN-1","name":"Torness Generator 1","cap":652},{"b":"T_TORN-2","name":"Torness Generator 2","cap":700}]},"way/100095758":{"units":[{"b":"T_TSREP-1","name":"MGT TEESIDE TEESREP MAIN","cap":285}]},"relation/8849887":{"units":[{"b":"E_TULWW-1","name":"Tullo Windfarm","cap":17}]},"relation/19293473":{"units":[{"b":"T_TYLNS-1","name":"Tye Lane Solar","cap":50}]},"relation/15748078":{"units":[{"b":"E_VKING-2","name":"Viking","cap":50},{"b":"T_VKNGW-1","name":"Viking Energy Windfarm BMU-1","cap":122},{"b":"T_VKNGW-2","name":"Viking Energy Windfarm BMU-2","cap":122},{"b":"T_VKNGW-3","name":"Viking Energy Windfarm BMU-3","cap":122},{"b":"T_VKNGW-4","name":"Viking Energy Windfarm BMU-4","cap":122}]},"way/160279522":{"units":[{"b":"T_WBUGT-1","name":"West Burton GT 01","cap":22},{"b":"T_WBUGT-4","name":"West Burton GT 04","cap":21},{"b":"T_WBURB-1","name":"West Burton B Unit 1","cap":470},{"b":"T_WBURB-2","name":"West Burton B Unit 2","cap":470},{"b":"T_WBURB-3","name":"West Burton B Unit 3","cap":470},{"b":"T_WBURB-41","name":"West Burton B Battery","cap":31},{"b":"T_WBURB-43","name":"West Burton B Battery","cap":31}]},"way/635728029":{"units":[{"b":"T_WDNSO-1","name":"West of Duddon Sands Offshore1","cap":197},{"b":"T_WDNSO-2","name":"West of Duddon Sands Offshore2","cap":201}]},"relation/15015645":{"units":[{"b":"T_WDRGW-1","name":"Windy Rig Wind Farm","cap":43}]},"relation/9599092":{"units":[{"b":"T_WHIHW-1","name":"Whiteside Hill WF","cap":28}]},"relation/2593160":{"units":[{"b":"T_WHILW-1","name":"T_WHILW-1","cap":309},{"b":"T_WHILW-2","name":"Whitelee Extension","cap":206}]},"way/1476530724":{"units":[{"b":"E_WHTBB-1","name":"Whitebirk BESS","cap":25}]},"way/77471728":{"units":[{"b":"T_WILCT-1","name":"ETOL - Wilton Site","cap":182}]},"relation/8829625":{"units":[{"b":"T_WLNYO-2","name":"WALNEY_2","cap":184},{"b":"T_WLNYO-3","name":"WALNEY_3","cap":330},{"b":"T_WLNYO-4","name":"WALNEY_4","cap":330},{"b":"T_WLNYO-4","name":"WALNEY_4","cap":330},{"b":"T_WLNYW-1","name":"WALNEY_1","cap":182}]},"way/1512631595":{"units":[{"b":"E_WOLVB-1","name":"Wolverhampton West BESS","cap":56}]},"way/341804043":{"units":[{"b":"T_WTMSO-1","name":"WESTERMOST_ROUGH","cap":205}]}},"sentinels":["T_TORN-1","T_HEYM11","T_HRTL-1","T_DRAXX-2"]}